{
  "AppVersion": "1.16.1.0",
  "CoreVersion": "30.6.1",
  "StartConversion": "2025/08/18 17:37:27 +10:00",
  "CodeCompletenessScore": "88",
  "TotalFiles": "47",
  "TotalFilesNotGenerated": "0",
  "ConversionSpeed": "994",
  "ElapsedTime": "00:00:07",
  "TotalConversionErrors": "59",
  "TotalParsingErrors": "389",
  "TotalWarnings": "26",
  "TotalLinesOfCode": "7350",
  "OutOfScopePercentage": "6",
  "InvalidExtensions": "1",
  "CodeUnitsOutOfScopePercentage": "0",
  "TotalNonParsingTransformationExceptions": "0",
  "TotalCodeUnits": "50",
  "TotalParsingEWIs": "386",
  "TotalOtherEWIs": "1069",
  "FullyConvertedCodeUnitsRate": "34",
  "FunctionalDifferenceMessages": "24",
  "PerformanceReviews": "0",
  "MissingDependentObjects": "3",
  "FilesWithUnexpectedEncoding": "2",
  "TotalIdentifiedObjects": "13",
  "ObjectConversionRate": "38.46",
  "ObjectsSuccessfullyConverted": "5",
  "UnrecognizedElements": "250",
  "UnrecognizedElementsLOC": "3304",
  "SqlTableObjectConversionRate": "38.46",
  "SqlTableTotalLinesOfCode": "406",
  "SqlTableTotalOccurrences": "13",
  "SqlTableTotalParsingErrors": "16",
  "SqlViewObjectConversionRate": "-",
  "SqlViewTotalLinesOfCode": "-",
  "SqlViewTotalOccurrences": "-",
  "SqlViewTotalParsingErrors": "-",
  "SqlProcedureObjectConversionRate": "-",
  "SqlProcedureTotalLinesOfCode": "-",
  "SqlProcedureTotalOccurrences": "-",
  "SqlProcedureTotalParsingErrors": "-",
  "ProcedureCursorOccurrences": "-",
  "ProcedureLoopOccurrences": "-",
  "FetchInLoop": "0",
  "ProceduresWithFetchInLoop": "0",
  "FunctionsWithFetchInLoop": "0",
  "BasicCursor": "0",
  "ProceduresWithBasicCursor": "0",
  "FunctionsWithBasicCursor": "0",
  "CursorForUpdate": "0",
  "ProceduresWithCursorForUpdate": "0",
  "FunctionsWithCursorForUpdate": "0",
  "FetchStatement": "0",
  "ProceduresWithFetchStatement": "0",
  "FunctionsWithFetchStatement": "0",
  "CursorsWithVariablesOrParameters": "0",
  "ProceduresWithCursorsWithVariablesOrParameters": "0",
  "FunctionsWithCursorsWithVariablesOrParameters": "0",
  "SqlFunctionObjectConversionRate": "-",
  "SqlFunctionTotalLinesOfCode": "-",
  "SqlFunctionTotalOccurrences": "-",
  "SqlFunctionTotalParsingErrors": "-",
  "LowIssues": "1010",
  "MediumIssues": "0",
  "HighIssues": "0",
  "CriticalIssues": "445",
  "ParsingIssues": "386",
  "OtherCriticalIssues": "59",
  "LowUniqueIssues": "3",
  "MediumUniqueIssues": "0",
  "HighUniqueIssues": "0",
  "CriticalUniqueIssues": "2",
  "UniqueParsingIssues": "1",
  "UniqueOtherCriticalIssues": "1",
  "Subqueries": "14",
  "CorrelatedSubqueries": "5",
  "SubqueriesWithMoreThanOneResultColumn": "0",
  "SubqueriesOutsideWhereClause": "0",
  "ViewsWithSubqueries": "0",
  "ViewsWithCorrelatedSubqueries": "0",
  "ViewsWithSubqueriesWithMoreThanOneResultColumn": "0",
  "ViewsWithSubqueriesOutsideWhereClause": "0",
  "ProceduresWithSubqueries": "0",
  "ProceduresWithCorrelatedSubqueries": "0",
  "ProceduresWithSubqueriesWithMoreThanOneResultColumn": "0",
  "ProceduresWithSubqueriesOutsideWhereClause": "0",
  "FunctionsWithSubqueries": "0",
  "FunctionsWithCorrelatedSubqueries": "0",
  "FunctionsWithSubqueriesWithMoreThanOneResultColumn": "0",
  "FunctionsWithSubqueriesOutsideWhereClause": "0",
  "DynamicTotalStatements": "0",
  "DynamicTotalTables": "0",
  "DynamicTotalViews": "0",
  "DynamicExecuteStatements": "0",
  "ProceduresWithDynamicExecuteStatements": "0",
  "FunctionsWithDynamicExecuteStatements": "0",
  "DynamicProcedureCallStatements": "0",
  "ProceduresWithDynamicProcedureCallStatements": "0",
  "FunctionsWithDynamicProcedureCallStatements": "0",
  "NestedCursors": "0",
  "ProceduresWithNestedCursors": "0",
  "FunctionsWithNestedCursors": "0",
  "ExternalTableObjectConversionRate": "-",
  "ExternalTableTotalLinesOfCode": "-",
  "ExternalTableTotalOccurrences": "-",
  "ExternalTableTotalParsingErrors": "-",
  "GrantStatements": "0",
  "GrantStatementLinesOfCode": "0",
  "Triggers": "0",
  "TriggerLinesOfCode": "0",
  "TotalFDMs": "24",
  "UniqueFDMs": "4",
  "TotalMissingObjectReferences": "9",
  "UniqueMissingObjectReferences": "3",
  "TotalPRFs": "0",
  "UniquePRFs": "0",
  "TotalLoCConversionRate": "21.61",
  "UnScopeJavaFunctionsObjects": "0",
  "UnScopeJavaFunctionsLoC": "0",
  "UnScopeCFunctionsObjects": "0",
  "UnScopeCFunctionsLoC": "0",
  "UnScopeJavaProceduresObjects": "0",
  "UnScopeJavaProceduresLoC": "0",
  "UnScopeCProceduresObjects": "0",
  "UnScopeCProceduresLoC": "0",
  "SqlLinesCount": "7350",
  "SqlTotalParsingErrors": "389",
  "SqlTableLoCConversionRate": "44.33",
  "SqlViewLoCConversionRate": "-",
  "SqlProcedureLoCConversionRate": "-",
  "SqlFunctionLoCConversionRate": "-",
  "ExternalTableLoCConversionRate": "-",
  "SqlFileCount": "49",
  "ScriptFileCount": "0",
  "SqlUnrecognizedElementsLOC": "3304",
  "ScriptTotalLoc": "0",
  "ScriptLocConversionRate": "0",
  "ScriptsUnrecognizedElementsLOC": "0",
  "SqlFilesConversionRate": "100",
  "SqlTotalConversionErrors": "142",
  "SqlTableTotalConversionErrors": "0",
  "SqlViewTotalConversionErrors": "-",
  "SqlProcedureTotalConversionErrors": "-",
  "SqlFunctionTotalConversionErrors": "-",
  "SqlJoinIndexObjectConversionRate": "-",
  "SqlJoinIndexLoCConversionRate": "-",
  "SqlJoinIndexTotalLinesOfCode": "-",
  "SqlJoinIndexTotalOccurrences": "-",
  "SqlJoinIndexTotalParsingErrors": "-",
  "SqlJoinIndexTotalConversionErrors": "-",
  "SqlMacroObjectConversionRate": "-",
  "SqlMacroLoCConversionRate": "-",
  "SqlMacroTotalLinesOfCode": "-",
  "SqlMacroTotalOccurrences": "-",
  "SqlMacroTotalParsingErrors": "-",
  "SqlMacroTotalConversionErrors": "-",
  "BTEQFilesConversionRate": "-",
  "BTEQLoCConversionRate": "-",
  "BTEQFileCount": "-",
  "BTEQLinesCount": "-",
  "BTEQTotalParsingErrors": "-",
  "BTEQTotalConversionErrors": "-",
  "FastLoadFilesConversionRate": "-",
  "FastLoadLoCConversionRate": "-",
  "FastLoadFileCount": "-",
  "FastLoadLinesCount": "-",
  "FastLoadTotalParsingErrors": "-",
  "FastLoadTotalConversionErrors": "-",
  "MultiLoadFilesConversionRate": "-",
  "MultiLoadLoCConversionRate": "-",
  "MultiLoadFileCount": "-",
  "MultiLoadLinesCount": "-",
  "MultiLoadTotalParsingErrors": "-",
  "MultiLoadTotalConversionErrors": "-",
  "TPTFilesConversionRate": "-",
  "TPTLoCConversionRate": "-",
  "TPTFileCount": "-",
  "TPTLinesCount": "-",
  "TPTTotalParsingErrors": "-",
  "TPTTotalConversionErrors": "-",
  "TPumpFilesConversionRate": "-",
  "TPumpLoCConversionRate": "-",
  "TPumpFileCount": "-",
  "TPumpLinesCount": "-",
  "TPumpTotalParsingErrors": "-",
  "TPumpTotalConversionErrors": "-",
  "ScriptTableObjectConversionRate": "-",
  "ScriptTableLoCConversionRate": "-",
  "ScriptTableTotalOccurrences": "-",
  "ScriptTableTotalLinesOfCode": "-",
  "ScriptTableTotalParsingErrors": "-",
  "ScriptTableTotalConversionErrors": "-",
  "ScriptViewObjectConversionRate": "-",
  "ScriptViewLoCConversionRate": "-",
  "ScriptViewTotalOccurrences": "-",
  "ScriptViewTotalLinesOfCode": "-",
  "ScriptViewTotalParsingErrors": "-",
  "ScriptViewTotalConversionErrors": "-",
  "ScriptJoinIndexObjectConversionRate": "-",
  "ScriptJoinIndexLoCConversionRate": "-",
  "ScriptJoinIndexTotalOccurrences": "-",
  "ScriptJoinIndexTotalLinesOfCode": "-",
  "ScriptJoinIndexTotalParsingErrors": "-",
  "ScriptJoinIndexTotalConversionErrors": "-",
  "ScriptMacroObjectConversionRate": "-",
  "ScriptMacroLoCConversionRate": "-",
  "ScriptMacroTotalOccurrences": "-",
  "ScriptMacroTotalLinesOfCode": "-",
  "ScriptMacroTotalParsingErrors": "-",
  "ScriptMacroTotalConversionErrors": "-",
  "ScriptProcedureObjectConversionRate": "-",
  "ScriptProcedureLoCConversionRate": "-",
  "ScriptProcedureTotalOccurrences": "-",
  "ScriptProcedureTotalLinesOfCode": "-",
  "ScriptProcedureTotalParsingErrors": "-",
  "ScriptProcedureTotalConversionErrors": "-",
  "ScriptFunctionObjectConversionRate": "-",
  "ScriptFunctionLoCConversionRate": "-",
  "ScriptFunctionTotalOccurrences": "-",
  "ScriptFunctionTotalLinesOfCode": "-",
  "ScriptFunctionTotalParsingErrors": "-",
  "ScriptFunctionTotalConversionErrors": "-",
  "TableObjectConversionRate": "38.46",
  "TableLoCConversionRate": "44.33",
  "TableTotalOccurrences": "13",
  "TableTotalLinesOfCode": "406",
  "TableTotalParsingErrors": "16",
  "TableTotalConversionErrors": "0",
  "ViewObjectConversionRate": "0",
  "ViewLoCConversionRate": "0",
  "ViewTotalOccurrences": "0",
  "ViewTotalLinesOfCode": "0",
  "ViewTotalParsingErrors": "0",
  "ViewTotalConversionErrors": "0",
  "JoinIndexObjectConversionRate": "0",
  "JoinIndexLoCConversionRate": "0",
  "JoinIndexTotalOccurrences": "0",
  "JoinIndexTotalLinesOfCode": "0",
  "JoinIndexTotalParsingErrors": "0",
  "JoinIndexTotalConversionErrors": "0",
  "MacroObjectConversionRate": "0",
  "MacroLoCConversionRate": "0",
  "MacroTotalOccurrences": "0",
  "MacroTotalLinesOfCode": "0",
  "MacroTotalParsingErrors": "0",
  "MacroTotalConversionErrors": "0",
  "ProcedureObjectConversionRate": "0",
  "ProcedureLoCConversionRate": "0",
  "ProcedureTotalOccurrences": "0",
  "ProcedureTotalLinesOfCode": "0",
  "ProcedureTotalParsingErrors": "0",
  "ProcedureTotalConversionErrors": "0",
  "FunctionObjectConversionRate": "0",
  "FunctionLoCConversionRate": "0",
  "FunctionTotalOccurrences": "0",
  "FunctionTotalLinesOfCode": "0",
  "FunctionTotalParsingErrors": "0",
  "FunctionTotalConversionErrors": "0",
  "TablesWithCheckConstraintColumnsConversionRate": "0",
  "TablesWithUniquePrimaryIndexColumnsConversionRate": "0",
  "TablesWithPrimaryKeyColumnsConversionRate": "0",
  "TablesWithForeignKeyColumnsConversionRate": "0",
  "TablesWithInvalidColumnNamesConversionRate": "0",
  "TablesWithColumnNamesThatRequireDoubleQuotesConversionRate": "0",
  "TablesWithSetOptionConversionRate": "0",
  "TablesWithTemporalColumnsConversionRate": "0",
  "TablesWithGlobalTemporaryOptionConversionRate": "0",
  "TablesWithQueueOptionConversionRate": "0",
  "TablesWithColumnsOfTypeNumberWithNoPrecisionConversionRate": "30.77",
  "TablesWithColumnsOfTypeIntervalConversionRate": "0",
  "TablesWithColumnsOfTypePeriodConversionRate": "0",
  "TablesWithColumnsOfTypeBlobConversionRate": "0",
  "TablesWithColumnsOfTypeClobConversionRate": "0",
  "TablesWithColumnsOfTypeGeospatialConversionRate": "0",
  "TablesWithColumnsOfTypeXmlOrJsonConversionRate": "0",
  "TablesWithBinaryTypeColumnsWithDefaultValueConversionRate": "0",
  "TablesWithTimeTypeColumnsWithDefaultValueConversionRate": "0",
  "TablesWithFloatTypeColumnsWithDefaultValueConversionRate": "0",
  "TablesWithIdentityDefaultValueColumnsConversionRate": "0",
  "TablesWithSessionDefaultValueColumnsConversionRate": "0",
  "TablesWithColumnsWithFormatSpecifiedConversionRate": "0",
  "TablesWithColumnsWithPartitionByOptionConversionRate": "0",
  "TablesWithColumnsWithUppercaseOptionConversionRate": "0",
  "CheckConstraintColumns": "0",
  "UniquePrimaryIndexColumns": "0",
  "PrimaryKeyColumns": "0",
  "ForeignKeyColumns": "0",
  "InvalidColumnNames": "0",
  "ColumnNamesThatRequireDoubleQuotes": "0",
  "SetOption": "0",
  "TemporalColumns": "0",
  "GlobalTemporaryOption": "0",
  "QueueOption": "0",
  "ColumnsOfTypeNumberWithNoPrecision": "20",
  "ColumnsOfTypeInterval": "0",
  "ColumnsOfTypePeriod": "0",
  "ColumnsOfTypeBlob": "0",
  "ColumnsOfTypeClob": "0",
  "ColumnsOfTypeGeospatial": "0",
  "ColumnsOfTypeXmlOrJson": "0",
  "BinaryTypeColumnsWithDefaultValue": "0",
  "TimeTypeColumnsWithDefaultValue": "0",
  "FloatTypeColumnsWithDefaultValue": "0",
  "IdentityDefaultValueColumns": "0",
  "SessionDefaultValueColumns": "0",
  "ColumnsWithUniqueConstraint": "No",
  "ColumnsWithFormatSpecified": "0",
  "UniqueFormatsCount": "No",
  "ColumnsWithPartitionByOption": "0",
  "ColumnsWithUppercaseOption": "0",
  "TablesWithCheckConstraintColumns": "0",
  "TablesWithUniquePrimaryIndexColumns": "0",
  "TablesWithPrimaryKeyColumns": "0",
  "TablesWithForeignKeyColumns": "0",
  "TablesWithInvalidColumnNames": "0",
  "TablesWithColumnNamesThatRequireDoubleQuotes": "0",
  "TablesWithSetOption": "0",
  "TablesWithTemporalColumns": "0",
  "TablesWithGlobalTemporaryOption": "0",
  "TablesWithQueueOption": "0",
  "TablesWithColumnsOfTypeNumberWithNoPrecision": "4",
  "TablesWithColumnsOfTypeInterval": "0",
  "TablesWithColumnsOfTypePeriod": "0",
  "TablesWithColumnsOfTypeBlob": "0",
  "TablesWithColumnsOfTypeClob": "0",
  "TablesWithColumnsOfTypeGeospatial": "0",
  "TablesWithColumnsOfTypeXmlOrJson": "0",
  "TablesWithBinaryTypeColumnsWithDefaultValue": "0",
  "TablesWithTimeTypeColumnsWithDefaultValue": "0",
  "TablesWithFloatTypeColumnsWithDefaultValue": "0",
  "TablesWithIdentityDefaultValueColumns": "0",
  "TablesWithSessionDefaultValueColumns": "0",
  "TablesWithColumnsWithFormatSpecified": "0",
  "TablesWithColumnsWithPartitionByOption": "0",
  "TablesWithColumnsWithUppercaseOption": "0",
  "ViewsWithMoreThanTenSelects": "0",
  "ProceduresWithOutOrInOutParameters": "0",
  "DynamicResultSetsCount": "0",
  "ActivityCountOcurrences": "0",
  "FunctionsWithSQLBody": "0",
  "NumberOfDatabasesThatContainObjects": "0",
  "FetchFirstOccurences": "0",
  "ProceduresWithFetchFirstOccurences": "0",
  "UpdateWhereCurrentOfOccurences": "0",
  "ProceduresWithUpdateWhereCurrentOfOccurences": "0",
  "DeleteWhereCurrentOfOccurences": "0",
  "ProceduresWithDeleteWhereCurrentOfOccurences": "0",
  "CursorForLoopOccurences": "0",
  "ProceduresWithCursorForLoopOccurences": "0",
  "MacrosWithCorrelatedSubqueries": "0",
  "MacrosWithSubqueries": "0",
  "MacrosWithSubqueriesInsideSubqueryOperators": "0",
  "MacrosWithSubqueriesOutsideWhereClause": "0",
  "MacrosWithSubqueriesWithMoreThanOneResultColumn": "0",
  "MacrosWithSubqueryOperatorsInsideOrOperators": "0",
  "MacrosWithSubqueryOperatorsOutsideWhereClause": "0",
  "JoinIndexesReferencingMultipleObjects": "0",
  "ViewsWithSelectAsteriskOnly": "0",
  "CaseInsensitiveCollationColumns": "0",
  "TablesWithCaseInsensitiveCollationColumns": "0",
  "TablesWithCaseInsensitiveCollationColumnsOccurrenceRate": "0",
  "CommentObjectsWithMissingDependencies": "Off",
  "DisableEwiCommentsGeneration": "Off",
  "SplitPeriodDatatype": "Off",
  "DisableTopologicalLevelReorder": "Off",
  "TargetLagValue": "1 days",
  "WarehouseName": "UPDATE_DUMMY_WAREHOUSE",
  "SessionMode": "TERA",
  "UseCollateForCaseSpecification": "Off",
  "GenerateXmlTagsForSqlStatementsInStoredProcedures": "Off",
  "EncodingOfTheInputFiles": "Unicode (UTF-8)",
  "CustomDatabaseName": "None",
  "CustomSchemaName": "None",
  "UseNoneSchema": "On",
  "UseExistingNameQualification": "Off",
  "KeepTeradataDatabaseAsSnowflakeDataWarehouse": "Off",
  "PrepareMyCodeForConversion": "Off",
  "CharacterToNumberDefaultScale": "10",
  "DefaultDateFormat": "YYYY/MM/DD",
  "DefaultTimeFormat": "HH:MI:SS",
  "DefaultTimestampFormat": "YYYY/MM/DD HH:MI:SS",
  "DefaultTimezoneFormat": "GMT-5",
  "BteqTargetLanguage": "Python",
  "ProceduresMacrosTargetLanguage": "Snowflake Scripting",
  "SqlTriggerObjectConversionRate": "-",
  "SqlTriggerLoCConversionRate": "-",
  "SqlTriggerTotalOccurrences": "-",
  "SqlTriggerTotalLinesOfCode": "-",
  "SqlTriggerTotalParsingErrors": "-",
  "SqlTriggerTotalConversionErrors": "-",
  "ScriptTriggerObjectConversionRate": "-",
  "ScriptTriggerLoCConversionRate": "-",
  "ScriptTriggerTotalOccurrences": "-",
  "ScriptTriggerTotalLinesOfCode": "-",
  "ScriptTriggerTotalParsingErrors": "-",
  "ScriptTriggerTotalConversionErrors": "-",
  "TriggerObjectConversionRate": "0",
  "TriggerLoCConversionRate": "0",
  "TriggerTotalOccurrences": "0",
  "TriggerTotalLinesOfCode": "0",
  "TriggerTotalParsingErrors": "0",
  "TriggerTotalConversionErrors": "0",
  "SqlIndexTotalOccurrences": "-",
  "SqlIndexTotalLinesOfCode": "-",
  "SqlIndexTotalParsingErrors": "-",
  "SqlIndexTotalConversionErrors": "-",
  "ScriptIndexTotalOccurrences": "-",
  "ScriptIndexTotalLinesOfCode": "-",
  "ScriptIndexTotalParsingErrors": "-",
  "ScriptIndexTotalConversionErrors": "-",
  "FunctionsWithUnsupportedLanguages": "0",
  "UnScopeCppFunctionsObjects": "0",
  "UnScopeCppFunctionsLoC": "0",
  "UnScopeCppProceduresObjects": "0",
  "UnScopeCppProceduresLoC": "0",
  "FilesNotGeneratedWarning01": "",
  "FilesNotGeneratedWarning02": "",
  "FilesNotGeneratedWarning03": "",
  "SnowScriptMark": "*",
  "SnowScriptNote": "*Stored Procedures were migrated to the Snowflake Scripting language.",
  "parsingIssuesDetails": [
    {
      "ErrorCode": "SSC-EWI-0001",
      "Description": "Error parsing the source code",
      "Instances": 386,
      "Level": "Critical",
      "ShowLevel": true,
      "DocumentationUrl": "https://docs.snowflake.com/en/migrations/snowconvert-docs/general/technical-documentation/issues-and-troubleshooting/conversion-issues/generalEWI#ssc-ewi-0001",
      "uri": "https://docs.snowflake.com/en/migrations/snowconvert-docs/general/technical-documentation/issues-and-troubleshooting/conversion-issues/generalEWI#ssc-ewi-0001"
    }
  ],
  "otherIssues": [
    {
      "ErrorCode": "SSC-EWI-0013",
      "Description": "Exception thrown during conversion",
      "Instances": 59,
      "Level": "Critical",
      "ShowLevel": true,
      "DocumentationUrl": "https://docs.snowflake.com/en/migrations/snowconvert-docs/general/technical-documentation/issues-and-troubleshooting/conversion-issues/generalEWI#ssc-ewi-0013",
      "uri": "https://docs.snowflake.com/en/migrations/snowconvert-docs/general/technical-documentation/issues-and-troubleshooting/conversion-issues/generalEWI#ssc-ewi-0013"
    },
    {
      "ErrorCode": "SSC-EWI-0040",
      "Description": "Statement Not Supported",
      "Instances": 1002,
      "Level": "Low",
      "ShowLevel": true,
      "DocumentationUrl": "https://docs.snowflake.com/en/migrations/snowconvert-docs/general/technical-documentation/issues-and-troubleshooting/conversion-issues/generalEWI#ssc-ewi-0040",
      "uri": "https://docs.snowflake.com/en/migrations/snowconvert-docs/general/technical-documentation/issues-and-troubleshooting/conversion-issues/generalEWI#ssc-ewi-0040"
    },
    {
      "ErrorCode": "SSC-EWI-TD0053",
      "Description": "Period types are handled as varchar",
      "Instances": 6,
      "Level": "Low",
      "ShowLevel": true,
      "DocumentationUrl": "https://docs.snowflake.com/en/migrations/snowconvert-docs/general/technical-documentation/issues-and-troubleshooting/conversion-issues/teradataEWI#ssc-ewi-td0053",
      "uri": "https://docs.snowflake.com/en/migrations/snowconvert-docs/general/technical-documentation/issues-and-troubleshooting/conversion-issues/teradataEWI#ssc-ewi-td0053"
    },
    {
      "ErrorCode": "SSC-EWI-TD0041",
      "Description": "Trunc added to ensure integer",
      "Instances": 2,
      "Level": "Low",
      "ShowLevel": true,
      "DocumentationUrl": "https://docs.snowflake.com/en/migrations/snowconvert-docs/general/technical-documentation/issues-and-troubleshooting/conversion-issues/teradataEWI#ssc-ewi-td0041",
      "uri": "https://docs.snowflake.com/en/migrations/snowconvert-docs/general/technical-documentation/issues-and-troubleshooting/conversion-issues/teradataEWI#ssc-ewi-td0041"
    }
  ],
  "unassessedScopeFiles": [
    {
      "FilePath": "storage",
      "FileSize": "56.0 KB",
      "Reason": "File Type"
    },
    {
      "FilePath": "DERV_ACCT_PATY_02_CRAT_WORK_TABL_CHG0379808.sql",
      "FileSize": "32.7 KB",
      "Reason": "Encoding (Unable to parse)"
    },
    {
      "FilePath": "DERV_ACCT_PATY_02_CRAT_WORK_TABL.sql",
      "FileSize": "45.7 KB",
      "Reason": "Encoding (Unable to parse)"
    }
  ],
  "functionalDifferenceMessagesDetails": [
    {
      "ErrorCode": "SSC-FDM-0007",
      "Description": "Element with missing dependencies",
      "Instances": 9,
      "Level": "None",
      "ShowLevel": false,
      "DocumentationUrl": "https://docs.snowflake.com/en/migrations/snowconvert-docs/general/technical-documentation/issues-and-troubleshooting/functional-difference/generalFDM#ssc-fdm-0007",
      "uri": "https://docs.snowflake.com/en/migrations/snowconvert-docs/general/technical-documentation/issues-and-troubleshooting/functional-difference/generalFDM#ssc-fdm-0007"
    },
    {
      "ErrorCode": "SSC-FDM-0008",
      "Description": "On Commit not supported",
      "Instances": 9,
      "Level": "None",
      "ShowLevel": false,
      "DocumentationUrl": "https://docs.snowflake.com/en/migrations/snowconvert-docs/general/technical-documentation/issues-and-troubleshooting/functional-difference/generalFDM#ssc-fdm-0008",
      "uri": "https://docs.snowflake.com/en/migrations/snowconvert-docs/general/technical-documentation/issues-and-troubleshooting/functional-difference/generalFDM#ssc-fdm-0008"
    },
    {
      "ErrorCode": "SSC-FDM-0002",
      "Description": "Correlated Subquery May Have Functional Differences.",
      "Instances": 5,
      "Level": "None",
      "ShowLevel": false,
      "DocumentationUrl": "https://docs.snowflake.com/en/migrations/snowconvert-docs/general/technical-documentation/issues-and-troubleshooting/functional-difference/generalFDM#ssc-fdm-0002",
      "uri": "https://docs.snowflake.com/en/migrations/snowconvert-docs/general/technical-documentation/issues-and-troubleshooting/functional-difference/generalFDM#ssc-fdm-0002"
    },
    {
      "ErrorCode": "SSC-FDM-TD0029",
      "Description": "Calling TO_CHAR can result in different behavior",
      "Instances": 1,
      "Level": "None",
      "ShowLevel": false,
      "DocumentationUrl": "https://docs.snowflake.com/en/migrations/snowconvert-docs/general/technical-documentation/issues-and-troubleshooting/functional-difference/teradataFDM#ssc-fdm-td0029",
      "uri": "https://docs.snowflake.com/en/migrations/snowconvert-docs/general/technical-documentation/issues-and-troubleshooting/functional-difference/teradataFDM#ssc-fdm-td0029"
    }
  ],
  "performanceReviewsDetails": [],
  "topLevelCodeUnits": [
    {
      "CodeUnitParentCategory": "DML",
      "CodeUnit": "DELETE",
      "FullyConvertedCodeUnitsConversionRate": 14.81,
      "LinesOfCodeConversionRate": 91.36,
      "TotalNumberOfCodeUnits": 27,
      "LinesOfCode": 509,
      "ParsingEWIs": 101,
      "OtherEWIs": 384
    },
    {
      "CodeUnitParentCategory": "DML",
      "CodeUnit": "UPDATE",
      "FullyConvertedCodeUnitsConversionRate": 100.0,
      "LinesOfCodeConversionRate": 100.0,
      "TotalNumberOfCodeUnits": 1,
      "LinesOfCode": 1,
      "ParsingEWIs": 0,
      "OtherEWIs": 0
    },
    {
      "CodeUnitParentCategory": "DQL",
      "CodeUnit": "SELECT",
      "FullyConvertedCodeUnitsConversionRate": 60.0,
      "LinesOfCodeConversionRate": 95.37,
      "TotalNumberOfCodeUnits": 5,
      "LinesOfCode": 108,
      "ParsingEWIs": 5,
      "OtherEWIs": 0
    },
    {
      "CodeUnitParentCategory": "TABLE",
      "CodeUnit": "CREATE TABLE",
      "FullyConvertedCodeUnitsConversionRate": 38.46,
      "LinesOfCodeConversionRate": 44.33,
      "TotalNumberOfCodeUnits": 13,
      "LinesOfCode": 406,
      "ParsingEWIs": 15,
      "OtherEWIs": 0
    },
    {
      "CodeUnitParentCategory": "TABLE",
      "CodeUnit": "DROP TABLE",
      "FullyConvertedCodeUnitsConversionRate": 100.0,
      "LinesOfCodeConversionRate": 100.0,
      "TotalNumberOfCodeUnits": 4,
      "LinesOfCode": 4,
      "ParsingEWIs": 0,
      "OtherEWIs": 0
    }
  ],
  "unassessedScopeCodeUnitsDetails": [
    {
      "Type": "Grant",
      "NumberOfObjects": 0,
      "LinesOfCode": 0
    },
    {
      "Type": "Trigger",
      "NumberOfObjects": 0,
      "LinesOfCode": 0
    }
  ],
  "unassessedScopeUnsupportedLanguageObjects": [
    {
      "Language": "Java",
      "Type": "Function",
      "NumberOfObjects": 0,
      "LinesOfCode": 0
    },
    {
      "Language": "Java",
      "Type": "Procedure",
      "NumberOfObjects": 0,
      "LinesOfCode": 0
    },
    {
      "Language": "C++",
      "Type": "Function",
      "NumberOfObjects": 0,
      "LinesOfCode": 0
    },
    {
      "Language": "C++",
      "Type": "Procedure",
      "NumberOfObjects": 0,
      "LinesOfCode": 0
    },
    {
      "Language": "C",
      "Type": "Function",
      "NumberOfObjects": 0,
      "LinesOfCode": 0
    },
    {
      "Language": "C",
      "Type": "Procedure",
      "NumberOfObjects": 0,
      "LinesOfCode": 0
    }
  ]
}